{
  "id": "019b4043-4399-7245-b44a-4d4fcd23a95b",
  "question": [
    "Generally, bears avoid winter by undergoing"
  ],
  "choices": [
    [
      "Aestivation"
    ],
    [
      "Diapause"
    ],
    [
      "Migration"
    ],
    [
      "Hibernation"
    ]
  ],
  "correctAnswer": 2,
  "explanation": [
    "Bears go into hibernation during winter to escape the cold weather.",
    "Aestivation is summer sleep, diapause is suspended development (zooplankton), and migration involves movement."
  ],
  "years": [
    2023
  ]
}