{
  "id": "a8be6ec7-38b2-4020-a8a4-4943be435dd7",
  "question": [
    "The chemical substances which are produced by some microbes which can kill or retard the growth of other microbes are known as"
  ],
  "choices": [
    [
      "Statins"
    ],
    [
      "Streptokinases"
    ],
    [
      "Cyclosporins"
    ],
    [
      "Antibiotics"
    ]
  ],
  "correctAnswer": 2,
  "explanation": [
    "Antibiotics are chemical substances produced by some microbes that kill or retard the growth of other disease-causing microbes."
  ],
  "years": [
    2024
  ]
}