{
  "id": "019b401d-7dfc-734a-9d7e-5309eb0c9be0",
  "question": [
    "A nucleus with mass number 220 initially at rest emits an alpha particle. If the Q value of reaction is 5.5 MeV, calculate the value of kinetic energy of alpha particle."
  ],
  "choices": [
    [
      "7.4 MeV"
    ],
    [
      "4.5 MeV"
    ],
    [
      "6.5 MeV"
    ],
    [
      "5.4 MeV"
    ]
  ],
  "correctAnswer": 2,
  "explanation": [
    "$K_{\\alpha} = \\frac{A-4}{A} Q = \\frac{216}{220} \\times 5.5 = 5.4$ MeV."
  ],
  "years": [
    2023
  ]
}