{
  "id": "019b401d-7df8-7798-b105-6dd01507e01a",
  "question": [
    "The torque acting on a magnetic dipole placed in uniform magnetic field is zero, when the angle between the dipole axis and the magnetic field is"
  ],
  "choices": [
    [
      "<katex>$60^{\\circ}$</katex>"
    ],
    [
      "<katex>$90^{\\circ}$</katex>"
    ],
    [
      "Zero"
    ],
    [
      "<katex>$45^{\\circ}$</katex>"
    ]
  ],
  "correctAnswer": 1,
  "explanation": [
    "The torque on a magnetic dipole is given by <katex>$\\tau = MB \\sin \\theta$</katex>.",
    "For the torque to be zero, <katex>$\\sin \\theta = 0$</katex>, which implies <katex>$\\theta = 0^{\\circ}$</katex> or <katex>$180^{\\circ}$</katex>."
  ],
  "years": [
    2023
  ]
}