{
  "id": "2025-phy-28",
  "question": [
    "Two thin long parallel wires separated by a distance 'r' from each other in vacuum carry a current of I ampere in opposite directions. Then, they will"
  ],
  "choices": [
    [
      "Attract each other with a force per unit length of <katex>$\\frac{\\mu_0 I^2}{2\\pi r}$</katex>"
    ],
    [
      "Repel each other with a force per unit length of <katex>$\\frac{\\mu_0 I^2}{2\\pi r}$</katex>"
    ],
    [
      "Repel each other with a force per unit length of <katex>$\\frac{\\mu_0 I^2}{2\\pi r^2}$</katex>"
    ],
    [
      "Attract each other with a force per unit length of <katex>$\\frac{\\mu_0 I^2}{2\\pi r^2}$</katex>"
    ]
  ],
  "correctAnswer": 0,
  "explanation": [
    "Force per unit length <katex>$\\frac{f}{l} = \\frac{\\mu_0 I_1 I_2}{2\\pi r}$</katex>. [cite: 468]",
    "If they carry opposite current they repel each other. [cite: 469]"
  ],
  "years": [
    2025
  ]
}