{
  "id": "019b403e-e58b-7f0b-978c-449ef61c8166",
  "question": [
    "Let $A=\\{x,y,z,u\\}$ and $B=\\{a,b\\}$. A function $f:A\\rightarrow B$ is selected randomly. The probability that the function is an onto function is"
  ],
  "choices": [
    [
      "$\\frac{5}{8}$"
    ],
    [
      "$\\frac{1}{35}$"
    ],
    [
      "$\\frac{7}{8}$"
    ],
    [
      "$\\frac{1}{8}$"
    ]
  ],
  "correctAnswer": 1,
  "explanation": [
    "Total functions $= |B|^{|A|} = 2^4 = 16$.",
    "Number of functions NOT onto (range size < 2): All map to 'a' (1) or all map to 'b' (1). Total 2.",
    "Onto functions $= 16 - 2 = 14$.",
    "Probability $= 14/16 = 7/8$."
  ],
  "years": [
    2023
  ]
}