{
  "id": "e1611d00-b7de-4015-b864-265bdba210b2",
  "question": [
    "The mean deviation about the mean for the data 4, 7, 8, 9, 10, 12, 13, 17 is"
  ],
  "choices": [
    [
      "10"
    ],
    [
      "3"
    ],
    [
      "8.5"
    ],
    [
      "4.03"
    ]
  ],
  "correctAnswer": 0,
  "explanation": [
    "Mean <katex>$\\mu = (4+7+8+9+10+12+13+17)/8 = 80/8 = 10$</katex>.",
    "Deviations <katex>$|x_i - \\mu|$</katex>: 6, 3, 2, 1, 0, 2, 3, 7.",
    "Mean Deviation = Sum(Deviations) / 8 = 24 / 8 = 3."
  ],
  "years": [
    2025
  ]
}